airhttprunner/__init__.py
airhttprunner/__main__.py
airhttprunner/app/__init__.py
airhttprunner/app/main.py
airhttprunner/app/routers/__init__.py
airhttprunner/app/routers/debug.py
airhttprunner/app/routers/debugtalk.py
airhttprunner/app/routers/deps.py
airhttprunner/builtin/__init__.py
airhttprunner/builtin/comparators.py
airhttprunner/builtin/functions.py
airhttprunner/cli.py
airhttprunner/client.py
airhttprunner/compat.py
airhttprunner/exceptions.py
airhttprunner/ext/__init__.py
airhttprunner/ext/har2case/__init__.py
airhttprunner/ext/har2case/core.py
airhttprunner/ext/har2case/utils.py
airhttprunner/ext/locust/__init__.py
airhttprunner/ext/locust/locustfile.py
airhttprunner/ext/uploader/__init__.py
airhttprunner/loader.py
airhttprunner/make.py
airhttprunner/models.py
airhttprunner/parser.py
airhttprunner/response.py
airhttprunner/runner.py
airhttprunner/scaffold.py
airhttprunner/testcase.py
airhttprunner/utils.py
docs/CHANGELOG.md
airhttprunner-3.1.5.dist-info/entry_points.txt
airhttprunner-3.1.5.dist-info/LICENSE
airhttprunner-3.1.5.dist-info/WHEEL
airhttprunner-3.1.5.dist-info/METADATA
airhttprunner-3.1.5.dist-info/RECORD
